session_shared_models/__init__.py
session_shared_models/py.typed
session_shared_models/state/__init__.py
session_shared_models/state/session_state.py
session_shared_models/state/state_message.py
session_shared_models-0.3.0.dist-info/METADATA
session_shared_models-0.3.0.dist-info/WHEEL
session_shared_models-0.3.0.dist-info/RECORD
