Metadata-Version: 2.3
Name: session-shared-models
Version: 0.3.0
Summary: Shared models for session management in the Auto Evaluation Bot
Author: ycalk
Author-email: alosev752@gmail.com
Requires-Python: >=3.11
Classifier: Programming Language :: Python :: 3
Classifier: Programming Language :: Python :: 3.11
Classifier: Programming Language :: Python :: 3.12
Classifier: Programming Language :: Python :: 3.13
Requires-Dist: pydantic (>=2.11.7,<3.0.0)
